dasp/__init__.py
dasp/algorithms.py
dasp/visualizations.py
dasp_stacker-0.1.1.dist-info/LICENSE
dasp_stacker-0.1.1.dist-info/METADATA
dasp_stacker-0.1.1.dist-info/WHEEL
dasp_stacker-0.1.1.dist-info/top_level.txt
dasp_stacker-0.1.1.dist-info/RECORD
