Metadata-Version: 2.1
Name: dasp-stacker
Version: 0.1.1
Summary: Dimensionally aligned signal projection library
Home-page: https://github.com/ORNL/DASP
Author: Jacob Smith
Keywords: signal processing,signal,visualization
Classifier: Programming Language :: Python :: 3
Classifier: Programming Language :: Python :: 3.9
Classifier: Programming Language :: Python :: 3.10
Classifier: License :: OSI Approved :: BSD License
Classifier: Operating System :: OS Independent
Classifier: Development Status :: 4 - Beta
Classifier: Intended Audience :: Science/Research
Requires-Python: >=3.9
License-File: LICENSE
Requires-Dist: numpy
Requires-Dist: scipy
Requires-Dist: ipywidgets
Requires-Dist: matplotlib
Requires-Dist: ipython
Requires-Dist: scikit-image
